nijika/__init__.py
nijika/core/__init__.py
nijika/core/agent.py
nijika/core/config.py
nijika/core/memory.py
nijika/core/providers.py
nijika/planning/__init__.py
nijika/planning/planner.py
nijika/rag/__init__.py
nijika/rag/system.py
nijika/tools/__init__.py
nijika/tools/registry.py
nijika/workflows/__init__.py
nijika/workflows/engine.py
nijika-1.0.0.dist-info/licenses/LICENSE
nijika-1.0.0.dist-info/METADATA
nijika-1.0.0.dist-info/WHEEL
nijika-1.0.0.dist-info/entry_points.txt
nijika-1.0.0.dist-info/top_level.txt
nijika-1.0.0.dist-info/RECORD
